<?xml version="1.0" encoding="utf-8"?>
<!DOCTYPE hibernate-mapping PUBLIC "-//Hibernate/Hibernate Mapping DTD 3.0//EN"
"http://www.hibernate.org/dtd/hibernate-mapping-3.0.dtd">
<hibernate-mapping>
	<class name="com.fis.mkc.domain.model.basic.BasicInstitution"
		entity-name="com.fis.mkc.domain.model.Institution" table="MKC_INST"
		mutable="false">

		<composite-id name="id"
			class="com.fis.mkc.domain.identity.InstitutionId">
			<key-property name="institutionId">
				<column name="ID" />
			</key-property>
			<key-property name="sourceId">
				<column name="SOURCE_ID" />
			</key-property>
		</composite-id>

		<property name="code" type="java.lang.String">
			<column name="CODE" length="10" not-null="true" unique="true" />
		</property>

		<property name="description" type="java.lang.String">
			<column name="DESCRIPTION" length="64" not-null="true" />
		</property>

		<property name="restrictionType" type="RestrictionType">
			<column name="TYPE_ID" />
		</property>

		<many-to-one name="source"
			entity-name="com.fis.mkc.domain.model.Source"
			insert="false" update="false">
			<column name="SOURCE_ID" />
		</many-to-one>
		
	</class>
</hibernate-mapping>